pynalyzer/__init__.py
pynalyzer/commands_handling/__init__.py
pynalyzer/commands_handling/command_executor.py
pynalyzer/commands_handling/command_preparer.py
pynalyzer/commands_handling/command_runner.py
pynalyzer/configuration_parsing/__init__.py
pynalyzer/configuration_parsing/configuration.py
pynalyzer/configuration_parsing/configuration_decoder.py
pynalyzer/configuration_parsing/configuration_parser.py
pynalyzer/configuration_parsing/configuration_path_finder.py
pynalyzer/scripts/__init__.py
pynalyzer/scripts/entrypoint.py
pynalyzer/utils/__init__.py
pynalyzer/utils/constants.py
pynalyzer/utils/converters.py
pynalyzer/utils/exceptions.py
pynalyzer-1.0.0.dist-info/LICENSE
pynalyzer-1.0.0.dist-info/METADATA
pynalyzer-1.0.0.dist-info/WHEEL
pynalyzer-1.0.0.dist-info/entry_points.txt
pynalyzer-1.0.0.dist-info/RECORD
