Metadata-Version: 2.1
Name: pynalyzer
Version: 1.0.0
Summary: Meta code analysis tool, bundling together multiple code analysis libraries
Home-page: https://github.com/Devourian/pynalyzer
License: MIT
Keywords: automation,code_quality,static_code_analysis,code_analysis,black,mypy,isort,bandit,cicd
Author: Devourian
Author-email: dorian.antonkiewicz@gmail.com
Maintainer: Devourian
Maintainer-email: dorian.antonkiewicz@gmail.com
Requires-Python: >=3.7,<4.0
Classifier: Development Status :: 4 - Beta
Classifier: Environment :: Console
Classifier: Intended Audience :: Developers
Classifier: License :: OSI Approved :: MIT License
Classifier: Operating System :: OS Independent
Classifier: Programming Language :: Python :: 3
Classifier: Programming Language :: Python :: 3.7
Classifier: Programming Language :: Python :: 3.8
Classifier: Programming Language :: Python :: 3.9
Classifier: Programming Language :: Python :: 3.10
Classifier: Programming Language :: Python :: 3.11
Classifier: Topic :: Software Development :: Libraries :: Python Modules
Classifier: Topic :: Software Development :: Quality Assurance
Classifier: Typing :: Typed
Requires-Dist: bandit (>=1.7.5,<2.0.0)
Requires-Dist: black (>=23.3.0,<24.0.0)
Requires-Dist: isort (>=5.11.5,<6.0.0)
Requires-Dist: mypy (>=1.4.1,<2.0.0)
Requires-Dist: tomli (>=2.0.1,<3.0.0) ; python_version < "3.11"
Project-URL: Repository, https://github.com/Devourian/pynalyzer
